{"version":"1.0.0","orisCode":8049,"monitoringPlanCommentData":[],"unitStackConfigurationData":[],"monitoringLocationData":[{"unitId":"**13","stackPipeId":null,"activeDate":null,"retireDate":null,"nonLoadBasedIndicator":0,"monitoringLocationAttribData":[{"ductIndicator":null,"bypassIndicator":null,"groundElevation":74,"stackHeight":56,"materialCode":null,"shapeCode":null,"crossAreaFlow":null,"crossAreaStackExit":150,"beginDate":"2001-01-01","endDate":null}],"unitCapacityData":[{"maximumHourlyHeatInputCapacity":954,"beginDate":"2002-10-31","endDate":"2012-11-08"},{"maximumHourlyHeatInputCapacity":1768.9,"beginDate":"2012-11-09","endDate":null}],"unitControlData":[{"parameterCode":"NOX","controlCode":"DLNB","originalCode":"1","installDate":null,"optimizationDate":null,"seasonalControlsIndicator":null,"retireDate":null},{"parameterCode":"NOX","controlCode":"H2O","originalCode":"1","installDate":null,"optimizationDate":null,"seasonalControlsIndicator":null,"retireDate":null}],"unitFuelData":[{"fuelCode":"DSL","indicatorCode":"S","ozoneSeasonIndicator":0,"demGCV":null,"demSO2":null,"beginDate":"2001-01-27","endDate":null},{"fuelCode":"PNG","indicatorCode":"P","ozoneSeasonIndicator":0,"demGCV":null,"demSO2":null,"beginDate":"2001-01-27","endDate":null}],"monitoringMethodData":[{"parameterCode":"HI","monitoringMethodCode":"AD","substituteDataCode":"SPTS","bypassApproachCode":null,"beginDate":"2001-01-27","beginHour":0,"endDate":null,"endHour":null},{"parameterCode":"NOX","monitoringMethodCode":"NOXR","substituteDataCode":null,"bypassApproachCode":null,"beginDate":"2008-01-01","beginHour":0,"endDate":"2016-12-31","endHour":23},{"parameterCode":"NOXR","monitoringMethodCode":"CEM","substituteDataCode":"SPTS","bypassApproachCode":null,"beginDate":"2001-01-27","beginHour":0,"endDate":null,"endHour":null},{"parameterCode":"OP","monitoringMethodCode":"EXP","substituteDataCode":null,"bypassApproachCode":null,"beginDate":"2001-01-27","beginHour":0,"endDate":null,"endHour":null},{"parameterCode":"SO2","monitoringMethodCode":"AD","substituteDataCode":"SPTS","bypassApproachCode":null,"beginDate":"2001-01-27","beginHour":0,"endDate":null,"endHour":null},{"parameterCode":"CO2M","monitoringMethodCode":"FSA","substituteDataCode":"SPTS","bypassApproachCode":null,"beginDate":"2001-01-27","beginHour":0,"endDate":"2008-09-30","endHour":23},{"parameterCode":"CO2","monitoringMethodCode":"AD","substituteDataCode":"SPTS","bypassApproachCode":null,"beginDate":"2008-10-01","beginHour":0,"endDate":null,"endHour":null}],"supplementalMATSMonitoringMethodData":[],"monitoringFormulaData":[{"parameterCode":"NOXR","formulaCode":"F-6","formulaId":"407","beginDate":"2001-01-27","beginHour":0,"endDate":"2011-09-25","endHour":23,"formulaText":null},{"parameterCode":"OILM","formulaCode":"D-3","formulaId":"408","beginDate":"2001-01-27","beginHour":0,"endDate":"2001-01-27","endHour":23,"formulaText":"Moil = S#(001-131) * Density oil"},{"parameterCode":"HI","formulaCode":"F-20","formulaId":"405","beginDate":"2001-01-27","beginHour":0,"endDate":null,"endHour":null,"formulaText":"HIg = S#(003-132) * GCVg / 1 * E6"},{"parameterCode":"NOX","formulaCode":"F-24A","formulaId":"415","beginDate":"2008-01-01","beginHour":0,"endDate":"2016-12-31","endHour":23,"formulaText":"M_h(lbs) = Eh (in lb/mmBtu) * HI (in mmBtu/hr) * Unit Operating Time (in hours)"},{"parameterCode":"HI","formulaCode":"F-19","formulaId":"404","beginDate":"2001-01-27","beginHour":0,"endDate":null,"endHour":null,"formulaText":"HIo = F#(408) * GCVo / 10**6"},{"parameterCode":"NOXR","formulaCode":"F-6","formulaId":"406","beginDate":"2001-01-27","beginHour":0,"endDate":null,"endHour":null,"formulaText":null},{"parameterCode":"SO2","formulaCode":"D-5","formulaId":"403","beginDate":"2001-01-27","beginHour":0,"endDate":null,"endHour":null,"formulaText":"M(SO2g) = 0.0006 * F#(405)"},{"parameterCode":"SO2","formulaCode":"D-2","formulaId":"402","beginDate":"2001-01-27","beginHour":0,"endDate":null,"endHour":null,"formulaText":"M(SO2) = 2.0 * F#(408) * %S / 100"},{"parameterCode":"CO2M","formulaCode":"G-1","formulaId":"401","beginDate":"2001-01-27","beginHour":0,"endDate":"2008-09-30","endHour":23,"formulaText":"WCO2 = [(MWc + MWo2) * Wc] / (2000 * MWc)"},{"parameterCode":"SO2","formulaCode":"D-12","formulaId":"441","beginDate":"2001-01-27","beginHour":0,"endDate":null,"endHour":null,"formulaText":null},{"parameterCode":"CO2","formulaCode":"G-4","formulaId":"413","beginDate":"2011-01-01","beginHour":0,"endDate":null,"endHour":null,"formulaText":null},{"parameterCode":"CO2","formulaCode":"G-4A","formulaId":"452","beginDate":"2008-10-01","beginHour":0,"endDate":null,"endHour":null,"formulaText":null},{"parameterCode":"CO2","formulaCode":"G-4","formulaId":"400","beginDate":"2008-10-01","beginHour":0,"endDate":null,"endHour":null,"formulaText":null},{"parameterCode":"HI","formulaCode":"D-15A","formulaId":"440","beginDate":"2001-01-27","beginHour":0,"endDate":null,"endHour":null,"formulaText":null}],"monitoringDefaultData":[{"parameterCode":"NORX","defaultValue":2.713,"defaultUnitsOfMeasureCode":"LBMMBTU","defaultPurposeCode":"MD","fuelCode":"NFS","operatingConditionCode":"A","defaultSourceCode":"DEF","groupId":null,"beginDate":"2001-01-27","beginHour":0,"endDate":null,"endHour":null},{"parameterCode":"CO2N","defaultValue":1,"defaultUnitsOfMeasureCode":"PCT","defaultPurposeCode":"DC","fuelCode":"NFS","operatingConditionCode":"A","defaultSourceCode":"DEF","groupId":null,"beginDate":"2001-01-27","beginHour":0,"endDate":null,"endHour":null},{"parameterCode":"SO2R","defaultValue":0.0006,"defaultUnitsOfMeasureCode":"LBMMBTU","defaultPurposeCode":"F23","fuelCode":"PNG","operatingConditionCode":"A","defaultSourceCode":"DEF","groupId":null,"beginDate":"2001-01-27","beginHour":0,"endDate":null,"endHour":null}],"monitoringSpanData":[{"componentTypeCode":"NOX","spanScaleCode":"L","spanMethodCode":"PL","mecValue":20,"mpcValue":null,"mpfValue":null,"spanValue":30,"fullScaleRange":30,"spanUnitsOfMeasureCode":"PPM","scaleTransitionPoint":25,"defaultHighRange":null,"flowSpanValue":null,"flowFullScaleRange":null,"beginDate":"2001-01-27","beginHour":0,"endDate":null,"endHour":null},{"componentTypeCode":"CO2","spanScaleCode":"H","spanMethodCode":"TB","mecValue":null,"mpcValue":6,"mpfValue":null,"spanValue":8,"fullScaleRange":10,"spanUnitsOfMeasureCode":"PCT","scaleTransitionPoint":null,"defaultHighRange":null,"flowSpanValue":null,"flowFullScaleRange":null,"beginDate":"2001-01-27","beginHour":0,"endDate":null,"endHour":null},{"componentTypeCode":"NOX","spanScaleCode":"H","spanMethodCode":"OL","mecValue":20,"mpcValue":160,"mpfValue":null,"spanValue":200,"fullScaleRange":200,"spanUnitsOfMeasureCode":"PPM","scaleTransitionPoint":25,"defaultHighRange":null,"flowSpanValue":null,"flowFullScaleRange":null,"beginDate":"2001-01-27","beginHour":0,"endDate":null,"endHour":null}],"rectangularDuctWAFData":[],"monitoringLoadData":[{"loadAnalysisDate":"2001-01-27","beginDate":"2001-01-27","beginHour":0,"endDate":"2002-06-30","endHour":23,"maximumLoadValue":97,"secondNormalIndicator":0,"upperOperationBoundary":95,"lowerOperationBoundary":10,"normalLevelCode":"H","secondLevelCode":"M","maximumLoadUnitsOfMeasureCode":"MW"},{"loadAnalysisDate":"2002-07-01","beginDate":"2002-07-01","beginHour":0,"endDate":null,"endHour":null,"maximumLoadValue":97,"secondNormalIndicator":1,"upperOperationBoundary":90,"lowerOperationBoundary":10,"normalLevelCode":"H","secondLevelCode":"M","maximumLoadUnitsOfMeasureCode":"MW"}],"componentData":[{"componentId":"004","componentTypeCode":"NOX","sampleAcquisitionMethodCode":"DOU","basisCode":"W","manufacturer":"TECO","modelVersion":"42C","serialNumber":"42C-66193-351","hgConverterIndicator":null,"analyzerRangeData":[{"analyzerRangeCode":"A","dualRangeIndicator":1,"beginDate":"2001-01-27","endDate":"2014-11-20","beginHour":0,"endHour":16}]},{"componentId":"001","componentTypeCode":"OFFM","sampleAcquisitionMethodCode":"PDP","basisCode":null,"manufacturer":"BROOKS FLOW METER","modelVersion":"B060 A","serialNumber":"0001-U001456-1-1","hgConverterIndicator":null,"analyzerRangeData":[]},{"componentId":"005","componentTypeCode":"CO2","sampleAcquisitionMethodCode":"DOU","basisCode":"W","manufacturer":"CALIFORNIA ANALYTICAL","modelVersion":"MODEL ZRH1","serialNumber":"A0H0090T","hgConverterIndicator":null,"analyzerRangeData":[{"analyzerRangeCode":"H","dualRangeIndicator":0,"beginDate":"2001-01-27","endDate":"2014-11-20","beginHour":0,"endHour":16}]},{"componentId":"002","componentTypeCode":"DAHS","sampleAcquisitionMethodCode":null,"basisCode":null,"manufacturer":"VIM TECHNOLOGIES","modelVersion":"CEMLINK 6","serialNumber":"CEM6.1","hgConverterIndicator":null,"analyzerRangeData":[]},{"componentId":"003","componentTypeCode":"GFFM","sampleAcquisitionMethodCode":"ORF","basisCode":null,"manufacturer":"TRIAD","modelVersion":"6\", 300# FLANGE","serialNumber":"202770","hgConverterIndicator":null,"analyzerRangeData":[]},{"componentId":"009","componentTypeCode":"OFFM","sampleAcquisitionMethodCode":"PDP","basisCode":null,"manufacturer":"BROOKS FLOW METER","modelVersion":"B060A P-STYLE","serialNumber":"0001-U001457-1-1","hgConverterIndicator":null,"analyzerRangeData":[]},{"componentId":"008","componentTypeCode":"PRB","sampleAcquisitionMethodCode":"DOU","basisCode":null,"manufacturer":"M&C","modelVersion":"SP2000H/DIL/BR","serialNumber":"7003/10024186","hgConverterIndicator":null,"analyzerRangeData":[]},{"componentId":"007","componentTypeCode":"CO2","sampleAcquisitionMethodCode":"DOU","basisCode":"W","manufacturer":"CAI","modelVersion":"600","serialNumber":"B08045","hgConverterIndicator":null,"analyzerRangeData":[{"analyzerRangeCode":"H","dualRangeIndicator":0,"beginDate":"2014-11-20","endDate":null,"beginHour":17,"endHour":null}]},{"componentId":"006","componentTypeCode":"NOX","sampleAcquisitionMethodCode":"DOU","basisCode":"W","manufacturer":"TECO","modelVersion":"42I","serialNumber":"1429362967","hgConverterIndicator":null,"analyzerRangeData":[{"analyzerRangeCode":"A","dualRangeIndicator":1,"beginDate":"2014-11-20","endDate":null,"beginHour":17,"endHour":null}]}],"monitoringSystemData":[{"monitoringSystemId":"132","systemTypeCode":"GAS","systemDesignationCode":"P","fuelCode":"PNG","beginDate":"2001-01-27","endDate":null,"beginHour":0,"endHour":null,"monitoringSystemComponentData":[{"componentId":"003","beginDate":"2001-01-27","beginHour":0,"endDate":null,"endHour":null},{"componentId":"002","beginDate":"2001-01-27","beginHour":0,"endDate":"2011-10-13","endHour":23},{"componentId":"002","beginDate":"2011-10-14","beginHour":0,"endDate":null,"endHour":null}],"monitoringSystemFuelFlowData":[{"maximumFuelFlowRate":11800,"systemFuelFlowUnitsOfMeasureCode":"HSCF","maximumFuelFlowRateSourceCode":"URV","beginDate":"2001-01-27","endDate":null,"beginHour":0,"endHour":null}]},{"monitoringSystemId":"131","systemTypeCode":"OILM","systemDesignationCode":"P","fuelCode":"DSL","beginDate":"2001-01-27","endDate":null,"beginHour":0,"endHour":null,"monitoringSystemComponentData":[{"componentId":"002","beginDate":"2001-01-27","beginHour":0,"endDate":"2011-10-13","endHour":23},{"componentId":"001","beginDate":"2004-12-22","beginHour":12,"endDate":"2020-12-31","endHour":12},{"componentId":"002","beginDate":"2011-10-14","beginHour":0,"endDate":null,"endHour":null},{"componentId":"009","beginDate":"2020-12-31","beginHour":13,"endDate":null,"endHour":null}],"monitoringSystemFuelFlowData":[{"maximumFuelFlowRate":105035,"systemFuelFlowUnitsOfMeasureCode":"LBHR","maximumFuelFlowRateSourceCode":"URV","beginDate":"2001-01-27","endDate":null,"beginHour":0,"endHour":null}]},{"monitoringSystemId":"133","systemTypeCode":"NOX","systemDesignationCode":"P","fuelCode":"NFS","beginDate":"2001-01-27","endDate":null,"beginHour":0,"endHour":null,"monitoringSystemComponentData":[{"componentId":"005","beginDate":"2001-01-27","beginHour":0,"endDate":"2014-11-20","endHour":16},{"componentId":"002","beginDate":"2001-01-27","beginHour":0,"endDate":"2011-10-13","endHour":23},{"componentId":"004","beginDate":"2001-01-27","beginHour":0,"endDate":"2014-11-20","endHour":16},{"componentId":"007","beginDate":"2014-11-20","beginHour":17,"endDate":null,"endHour":null},{"componentId":"006","beginDate":"2014-11-20","beginHour":17,"endDate":null,"endHour":null},{"componentId":"008","beginDate":"2001-01-27","beginHour":0,"endDate":null,"endHour":null},{"componentId":"002","beginDate":"2011-10-14","beginHour":0,"endDate":null,"endHour":null}],"monitoringSystemFuelFlowData":[]}],"monitoringQualificationData":[]}]}