{"version":"1.0.0","orisCode":55201,"monitoringPlanCommentData":[{"monitoringPlanComment":"The thermo 42i contains the 48i O2 sensor within. ","beginDate":"2019-05-21","endDate":null},{"monitoringPlanComment":"CF for 2018 and 2019 revised for the 2021 PK verification.  The new 2018 and 2019 CF includes data substitution.  Previously used annubar fuel flowmeters included certification errors, which necessitated data substitution to correct certification issues.  Even with the higher heat input values used for data substitution, the facility has confirmed that no single year CF was >20% and no 3-year average was >10% and PK status is confirmed.","beginDate":"2021-01-01","endDate":null}],"unitStackConfigurationData":[],"monitoringLocationData":[{"unitId":"GCTG2","stackPipeId":null,"activeDate":null,"retireDate":null,"nonLoadBasedIndicator":0,"monitoringLocationAttribData":[{"ductIndicator":null,"bypassIndicator":null,"groundElevation":752,"stackHeight":50,"materialCode":null,"shapeCode":null,"crossAreaFlow":null,"crossAreaStackExit":459,"beginDate":"2000-09-04","endDate":null}],"unitCapacityData":[{"maximumHourlyHeatInputCapacity":1459,"beginDate":"2002-10-31","endDate":"2014-12-31"},{"maximumHourlyHeatInputCapacity":1236,"beginDate":"2017-01-01","endDate":"2017-12-31"},{"maximumHourlyHeatInputCapacity":1308,"beginDate":"2016-01-22","endDate":"2016-12-31"},{"maximumHourlyHeatInputCapacity":1400,"beginDate":"2020-01-01","endDate":null},{"maximumHourlyHeatInputCapacity":1657,"beginDate":"2018-01-01","endDate":"2019-06-30"},{"maximumHourlyHeatInputCapacity":1259,"beginDate":"2015-01-01","endDate":"2016-01-21"},{"maximumHourlyHeatInputCapacity":1300,"beginDate":"2019-07-01","endDate":"2019-12-31"}],"unitControlData":[{"parameterCode":"NOX","controlCode":"DLNB","originalCode":"1","installDate":null,"optimizationDate":null,"seasonalControlsIndicator":"0","retireDate":null},{"parameterCode":"NOX","controlCode":"H2O","originalCode":"1","installDate":null,"optimizationDate":null,"seasonalControlsIndicator":"0","retireDate":null}],"unitFuelData":[{"fuelCode":"PNG","indicatorCode":"P","ozoneSeasonIndicator":0,"demGCV":null,"demSO2":null,"beginDate":"2000-07-22","endDate":null},{"fuelCode":"DSL","indicatorCode":"S","ozoneSeasonIndicator":0,"demGCV":null,"demSO2":null,"beginDate":"2000-07-22","endDate":null}],"monitoringMethodData":[{"parameterCode":"SO2","monitoringMethodCode":"AD","substituteDataCode":"SPTS","bypassApproachCode":null,"beginDate":"2000-09-04","beginHour":0,"endDate":null,"endHour":null},{"parameterCode":"CO2","monitoringMethodCode":"AD","substituteDataCode":"SPTS","bypassApproachCode":null,"beginDate":"2000-09-04","beginHour":0,"endDate":null,"endHour":null},{"parameterCode":"HI","monitoringMethodCode":"AD","substituteDataCode":"SPTS","bypassApproachCode":null,"beginDate":"2000-09-04","beginHour":0,"endDate":null,"endHour":null},{"parameterCode":"NOX","monitoringMethodCode":"NOXR","substituteDataCode":null,"bypassApproachCode":null,"beginDate":"2003-01-01","beginHour":0,"endDate":null,"endHour":null},{"parameterCode":"NOXR","monitoringMethodCode":"CEM","substituteDataCode":"SPTS","bypassApproachCode":null,"beginDate":"2000-09-04","beginHour":0,"endDate":null,"endHour":null},{"parameterCode":"OP","monitoringMethodCode":"EXP","substituteDataCode":null,"bypassApproachCode":null,"beginDate":"2000-09-04","beginHour":0,"endDate":null,"endHour":null}],"supplementalMATSMonitoringMethodData":[],"monitoringFormulaData":[{"parameterCode":"NOXR","formulaCode":"F-5","formulaId":"N2A","beginDate":"2000-09-04","beginHour":0,"endDate":null,"endHour":null,"formulaText":"NOx = 1.194 * 10-7 * S#(G21-G2N) *  F#(F2D) * 20.9/(20.9 / S#(G22-G2N))"},{"parameterCode":"HI","formulaCode":"F-19","formulaId":"H2O","beginDate":"2000-09-04","beginHour":0,"endDate":null,"endHour":null,"formulaText":"HI(oil) = S#(G24-G2O) * (GCVoil / 1,000,000)"},{"parameterCode":"FD","formulaCode":"F-8","formulaId":"F2D","beginDate":"2000-09-04","beginHour":0,"endDate":null,"endHour":null,"formulaText":"Fd = F#(H2G) * 8710 * T(gas) + F#(H2O) * 9190 * T(oil) / F#(H2C) * T_1"},{"parameterCode":"HI","formulaCode":"D-15A","formulaId":"H2C","beginDate":"2000-07-01","beginHour":0,"endDate":null,"endHour":null,"formulaText":"HI_t = (F#(H2G) * T(gas) + F#(H2O) * T(oil)) / T_2"},{"parameterCode":"SO2","formulaCode":"D-2","formulaId":"S2O","beginDate":"2000-09-04","beginHour":0,"endDate":null,"endHour":null,"formulaText":"SO2(oil) = 2 * S#(G24-G2O) * %S(oil) / 100"},{"parameterCode":"NOX","formulaCode":"F-24A","formulaId":"N2B","beginDate":"2003-01-01","beginHour":0,"endDate":null,"endHour":null,"formulaText":"M_NOx_h = F#(N2A) * F#(H2C) * t_h"},{"parameterCode":"CO2","formulaCode":"G-4A","formulaId":"C2A","beginDate":"2000-09-04","beginHour":0,"endDate":null,"endHour":null,"formulaText":null},{"parameterCode":"SO2","formulaCode":"D-5","formulaId":"S2G","beginDate":"2000-09-04","beginHour":0,"endDate":null,"endHour":null,"formulaText":"SO2(gas) = 0.0006 * F#(H2G)"},{"parameterCode":"FC","formulaCode":"F-8","formulaId":"F2C","beginDate":"2000-09-04","beginHour":0,"endDate":null,"endHour":null,"formulaText":"FC = F#(H2G) * 1040 * T(gas) + F#(H2O) * 1420 * T(oil) / F#(H2C) * T_1"},{"parameterCode":"HI","formulaCode":"F-20","formulaId":"H2G","beginDate":"2000-09-04","beginHour":0,"endDate":null,"endHour":null,"formulaText":"HI(gas) = S#(G23-G2G) * (GCVgas / 1,000,000)"},{"parameterCode":"CO2","formulaCode":"G-4","formulaId":"C2O","beginDate":"2000-09-04","beginHour":0,"endDate":null,"endHour":null,"formulaText":"WCO2(oil) = F#(F1C)*F#(H1O)*1/385*44/2000* 1/385 * 44/2000"},{"parameterCode":"SO2","formulaCode":"D-12","formulaId":"S2C","beginDate":"2000-09-04","beginHour":0,"endDate":null,"endHour":null,"formulaText":"SO2=(F#(S1G)*T(gas)+F#(S1O)*T(oil))/T(unit)"},{"parameterCode":"CO2","formulaCode":"G-4","formulaId":"C2G","beginDate":"2000-09-04","beginHour":0,"endDate":null,"endHour":null,"formulaText":"WCO2(gas) = F#(F1C)*F#(H1G* 1/385 * 44/2000"}],"monitoringDefaultData":[{"parameterCode":"NORX","defaultValue":0.206,"defaultUnitsOfMeasureCode":"LBMMBTU","defaultPurposeCode":"MD","fuelCode":"NFS","operatingConditionCode":"A","defaultSourceCode":"DEF","groupId":null,"beginDate":"2000-08-15","beginHour":0,"endDate":null,"endHour":null},{"parameterCode":"MNGF","defaultValue":1,"defaultUnitsOfMeasureCode":"HSCF","defaultPurposeCode":"DM","fuelCode":"PNG","operatingConditionCode":"A","defaultSourceCode":"DATA","groupId":null,"beginDate":"2007-01-01","beginHour":0,"endDate":null,"endHour":null},{"parameterCode":"MNOF","defaultValue":5.1,"defaultUnitsOfMeasureCode":"LBHR","defaultPurposeCode":"DM","fuelCode":"DSL","operatingConditionCode":"A","defaultSourceCode":"DATA","groupId":null,"beginDate":"2007-01-01","beginHour":0,"endDate":null,"endHour":null},{"parameterCode":"O2X","defaultValue":19,"defaultUnitsOfMeasureCode":"PCT","defaultPurposeCode":"DC","fuelCode":"NFS","operatingConditionCode":"A","defaultSourceCode":"DEF","groupId":null,"beginDate":"2000-07-22","beginHour":0,"endDate":null,"endHour":null},{"parameterCode":"SO2R","defaultValue":0.0006,"defaultUnitsOfMeasureCode":"LBMMBTU","defaultPurposeCode":"F23","fuelCode":"PNG","operatingConditionCode":"A","defaultSourceCode":"DEF","groupId":null,"beginDate":"2000-07-22","beginHour":0,"endDate":null,"endHour":null}],"monitoringSpanData":[{"componentTypeCode":"NOX","spanScaleCode":"H","spanMethodCode":"OL","mecValue":40,"mpcValue":56,"mpfValue":null,"spanValue":70,"fullScaleRange":100,"spanUnitsOfMeasureCode":"PPM","scaleTransitionPoint":null,"defaultHighRange":null,"flowSpanValue":null,"flowFullScaleRange":null,"beginDate":"2000-08-15","beginHour":0,"endDate":null,"endHour":null},{"componentTypeCode":"O2","spanScaleCode":"H","spanMethodCode":null,"mecValue":null,"mpcValue":null,"mpfValue":null,"spanValue":20,"fullScaleRange":25,"spanUnitsOfMeasureCode":"PCT","scaleTransitionPoint":null,"defaultHighRange":null,"flowSpanValue":null,"flowFullScaleRange":null,"beginDate":"2000-08-15","beginHour":0,"endDate":null,"endHour":null}],"rectangularDuctWAFData":[],"monitoringLoadData":[{"loadAnalysisDate":"2000-07-22","beginDate":"2000-09-04","beginHour":0,"endDate":"2003-06-30","endHour":23,"maximumLoadValue":135,"secondNormalIndicator":0,"upperOperationBoundary":135,"lowerOperationBoundary":75,"normalLevelCode":"H","secondLevelCode":"L","maximumLoadUnitsOfMeasureCode":"MW"},{"loadAnalysisDate":"2005-01-01","beginDate":"2005-01-01","beginHour":0,"endDate":"2005-09-30","endHour":23,"maximumLoadValue":135,"secondNormalIndicator":0,"upperOperationBoundary":135,"lowerOperationBoundary":75,"normalLevelCode":"M","secondLevelCode":"L","maximumLoadUnitsOfMeasureCode":"MW"},{"loadAnalysisDate":"2003-07-01","beginDate":"2003-07-01","beginHour":0,"endDate":"2006-12-31","endHour":23,"maximumLoadValue":135,"secondNormalIndicator":1,"upperOperationBoundary":135,"lowerOperationBoundary":75,"normalLevelCode":"M","secondLevelCode":"L","maximumLoadUnitsOfMeasureCode":"MW"},{"loadAnalysisDate":"2007-01-01","beginDate":"2007-01-01","beginHour":0,"endDate":"2015-07-29","endHour":23,"maximumLoadValue":135,"secondNormalIndicator":0,"upperOperationBoundary":135,"lowerOperationBoundary":75,"normalLevelCode":"L","secondLevelCode":"M","maximumLoadUnitsOfMeasureCode":"MW"},{"loadAnalysisDate":null,"beginDate":"2019-01-01","beginHour":0,"endDate":null,"endHour":null,"maximumLoadValue":135,"secondNormalIndicator":null,"upperOperationBoundary":135,"lowerOperationBoundary":75,"normalLevelCode":null,"secondLevelCode":null,"maximumLoadUnitsOfMeasureCode":"MW"},{"loadAnalysisDate":null,"beginDate":"2018-07-18","beginHour":0,"endDate":"2018-12-31","endHour":23,"maximumLoadValue":135,"secondNormalIndicator":null,"upperOperationBoundary":135,"lowerOperationBoundary":75,"normalLevelCode":null,"secondLevelCode":null,"maximumLoadUnitsOfMeasureCode":"MW"},{"loadAnalysisDate":"2015-07-30","beginDate":"2015-07-30","beginHour":0,"endDate":"2018-07-17","endHour":23,"maximumLoadValue":135,"secondNormalIndicator":1,"upperOperationBoundary":135,"lowerOperationBoundary":75,"normalLevelCode":"M","secondLevelCode":"H","maximumLoadUnitsOfMeasureCode":"MW"}],"componentData":[{"componentId":"G22","componentTypeCode":"O2","sampleAcquisitionMethodCode":"EXT","basisCode":"D","manufacturer":"MONITOR LABS","modelVersion":"422","serialNumber":"01420C/1256","hgConverterIndicator":null,"analyzerRangeData":[{"analyzerRangeCode":"H","dualRangeIndicator":0,"beginDate":"2000-09-04","endDate":"2019-05-21","beginHour":0,"endHour":12}]},{"componentId":"G23","componentTypeCode":"GFFM","sampleAcquisitionMethodCode":"DP","basisCode":null,"manufacturer":"ROSEMOUNT","modelVersion":"DCR+25S","serialNumber":"308299R1.2","hgConverterIndicator":null,"analyzerRangeData":[]},{"componentId":"G24","componentTypeCode":"OFFM","sampleAcquisitionMethodCode":"TUR","basisCode":null,"manufacturer":"SPONSLER","modelVersion":"SP2CSPHLK4X","serialNumber":"211900","hgConverterIndicator":null,"analyzerRangeData":[]},{"componentId":"G25","componentTypeCode":"DAHS","sampleAcquisitionMethodCode":null,"basisCode":null,"manufacturer":"ESC","modelVersion":"STACKVISION","serialNumber":"33PPJ81","hgConverterIndicator":null,"analyzerRangeData":[]},{"componentId":"G21","componentTypeCode":"NOX","sampleAcquisitionMethodCode":"EXT","basisCode":"D","manufacturer":"MONITOR LABS","modelVersion":"9841AS","serialNumber":"329-160","hgConverterIndicator":null,"analyzerRangeData":[{"analyzerRangeCode":"H","dualRangeIndicator":0,"beginDate":"2000-09-04","endDate":"2019-05-21","beginHour":0,"endHour":12}]},{"componentId":"G26","componentTypeCode":"PRB","sampleAcquisitionMethodCode":"EXT","basisCode":null,"manufacturer":"UNIVERSAL ANALYZERS INC","modelVersion":"270S","serialNumber":"B7657","hgConverterIndicator":null,"analyzerRangeData":[]},{"componentId":"G27","componentTypeCode":"NOX","sampleAcquisitionMethodCode":"EXT","basisCode":"D","manufacturer":"THERMOSCIENTIFIC","modelVersion":"42I","serialNumber":"1190772086","hgConverterIndicator":null,"analyzerRangeData":[{"analyzerRangeCode":"H","dualRangeIndicator":0,"beginDate":"2019-05-21","endDate":null,"beginHour":13,"endHour":null}]},{"componentId":"G28","componentTypeCode":"O2","sampleAcquisitionMethodCode":"EXT","basisCode":"D","manufacturer":"THERMOSCIENTIFIC","modelVersion":"42I","serialNumber":"1190772086","hgConverterIndicator":null,"analyzerRangeData":[{"analyzerRangeCode":"H","dualRangeIndicator":0,"beginDate":"2019-05-21","endDate":null,"beginHour":13,"endHour":null}]},{"componentId":"G32","componentTypeCode":"GFFM","sampleAcquisitionMethodCode":"ORF","basisCode":null,"manufacturer":"ROSEMOUNT","modelVersion":"1495","serialNumber":"4254407175-02-001","hgConverterIndicator":null,"analyzerRangeData":[]}],"monitoringSystemData":[{"monitoringSystemId":"G2O","systemTypeCode":"OILM","systemDesignationCode":"P","fuelCode":"DSL","beginDate":"2000-09-04","endDate":null,"beginHour":0,"endHour":null,"monitoringSystemComponentData":[{"componentId":"G24","beginDate":"2001-07-06","beginHour":10,"endDate":null,"endHour":null},{"componentId":"G25","beginDate":"2000-09-04","beginHour":0,"endDate":null,"endHour":null}],"monitoringSystemFuelFlowData":[{"maximumFuelFlowRate":95040,"systemFuelFlowUnitsOfMeasureCode":"LBHR","maximumFuelFlowRateSourceCode":"UMX","beginDate":"2000-10-01","endDate":null,"beginHour":0,"endHour":null},{"maximumFuelFlowRate":80000,"systemFuelFlowUnitsOfMeasureCode":"LBHR","maximumFuelFlowRateSourceCode":"UMX","beginDate":"2000-09-04","endDate":"2000-09-30","beginHour":0,"endHour":23}]},{"monitoringSystemId":"G2G","systemTypeCode":"GAS","systemDesignationCode":"P","fuelCode":"PNG","beginDate":"2000-09-04","endDate":null,"beginHour":0,"endHour":null,"monitoringSystemComponentData":[{"componentId":"G23","beginDate":"2005-12-29","beginHour":10,"endDate":"2020-10-09","endHour":8},{"componentId":"G25","beginDate":"2000-09-04","beginHour":0,"endDate":null,"endHour":null},{"componentId":"G32","beginDate":"2020-10-09","beginHour":9,"endDate":null,"endHour":null}],"monitoringSystemFuelFlowData":[{"maximumFuelFlowRate":16000,"systemFuelFlowUnitsOfMeasureCode":"HSCF","maximumFuelFlowRateSourceCode":"UMX","beginDate":"2000-09-04","endDate":"2000-09-30","beginHour":0,"endHour":23},{"maximumFuelFlowRate":16000,"systemFuelFlowUnitsOfMeasureCode":"HSCF","maximumFuelFlowRateSourceCode":"UMX","beginDate":"2000-10-01","endDate":"2015-12-31","beginHour":0,"endHour":23},{"maximumFuelFlowRate":11984,"systemFuelFlowUnitsOfMeasureCode":"HSCF","maximumFuelFlowRateSourceCode":"UMX","beginDate":"2017-01-01","endDate":"2019-12-31","beginHour":0,"endHour":23},{"maximumFuelFlowRate":12701,"systemFuelFlowUnitsOfMeasureCode":"HSCF","maximumFuelFlowRateSourceCode":"UMX","beginDate":"2016-01-01","endDate":"2016-12-31","beginHour":0,"endHour":23},{"maximumFuelFlowRate":13245,"systemFuelFlowUnitsOfMeasureCode":"HSCF","maximumFuelFlowRateSourceCode":"UMX","beginDate":"2020-01-01","endDate":null,"beginHour":0,"endHour":null}]},{"monitoringSystemId":"G2N","systemTypeCode":"NOX","systemDesignationCode":"P","fuelCode":"NFS","beginDate":"2000-09-04","endDate":null,"beginHour":0,"endHour":null,"monitoringSystemComponentData":[{"componentId":"G22","beginDate":"2000-09-04","beginHour":0,"endDate":"2019-05-21","endHour":12},{"componentId":"G25","beginDate":"2000-09-04","beginHour":0,"endDate":null,"endHour":null},{"componentId":"G21","beginDate":"2000-09-04","beginHour":0,"endDate":"2019-05-21","endHour":12},{"componentId":"G26","beginDate":"2000-09-04","beginHour":0,"endDate":null,"endHour":null},{"componentId":"G28","beginDate":"2019-05-21","beginHour":13,"endDate":null,"endHour":null},{"componentId":"G27","beginDate":"2019-05-21","beginHour":13,"endDate":null,"endHour":null}],"monitoringSystemFuelFlowData":[]}],"monitoringQualificationData":[{"qualificationTypeCode":"PK","beginDate":"2016-01-01","endDate":null,"monitoringQualificationLEEData":[],"monitoringQualificationLMEData":[],"monitoringQualificationPercentData":[{"qualificationYear":2021,"averagePercentValue":6.6,"yr1QualificationDataYear":2018,"yr1QualificationDataTypeCode":"A","yr1PercentageValue":4.8,"yr2QualificationDataYear":2019,"yr2QualificationDataTypeCode":"A","yr2PercentageValue":4.9,"yr3QualificationDataYear":2020,"yr3QualificationDataTypeCode":"A","yr3PercentageValue":10},{"qualificationYear":2018,"averagePercentValue":2.8,"yr1QualificationDataYear":2015,"yr1QualificationDataTypeCode":"A","yr1PercentageValue":2.2,"yr2QualificationDataYear":2016,"yr2QualificationDataTypeCode":"A","yr2PercentageValue":4.3,"yr3QualificationDataYear":2017,"yr3QualificationDataTypeCode":"A","yr3PercentageValue":2},{"qualificationYear":2016,"averagePercentValue":1.1,"yr1QualificationDataYear":2013,"yr1QualificationDataTypeCode":"A","yr1PercentageValue":0,"yr2QualificationDataYear":2014,"yr2QualificationDataTypeCode":"A","yr2PercentageValue":1.1,"yr3QualificationDataYear":2015,"yr3QualificationDataTypeCode":"A","yr3PercentageValue":2.2},{"qualificationYear":2017,"averagePercentValue":2.5,"yr1QualificationDataYear":2014,"yr1QualificationDataTypeCode":"A","yr1PercentageValue":1.1,"yr2QualificationDataYear":2015,"yr2QualificationDataTypeCode":"A","yr2PercentageValue":2.2,"yr3QualificationDataYear":2016,"yr3QualificationDataTypeCode":"A","yr3PercentageValue":4.3},{"qualificationYear":2019,"averagePercentValue":3.3,"yr1QualificationDataYear":2016,"yr1QualificationDataTypeCode":"A","yr1PercentageValue":4.3,"yr2QualificationDataYear":2017,"yr2QualificationDataTypeCode":"A","yr2PercentageValue":2,"yr3QualificationDataYear":2018,"yr3QualificationDataTypeCode":"A","yr3PercentageValue":3.5},{"qualificationYear":2024,"averagePercentValue":3.8,"yr1QualificationDataYear":2021,"yr1QualificationDataTypeCode":"A","yr1PercentageValue":6.8,"yr2QualificationDataYear":2022,"yr2QualificationDataTypeCode":"A","yr2PercentageValue":1.3,"yr3QualificationDataYear":2023,"yr3QualificationDataTypeCode":"A","yr3PercentageValue":3.2},{"qualificationYear":2022,"averagePercentValue":4.3,"yr1QualificationDataYear":2019,"yr1QualificationDataTypeCode":"A","yr1PercentageValue":3.3,"yr2QualificationDataYear":2020,"yr2QualificationDataTypeCode":"A","yr2PercentageValue":3.1,"yr3QualificationDataYear":2021,"yr3QualificationDataTypeCode":"A","yr3PercentageValue":6.6},{"qualificationYear":2023,"averagePercentValue":6.5,"yr1QualificationDataYear":2020,"yr1QualificationDataTypeCode":"A","yr1PercentageValue":10,"yr2QualificationDataYear":2021,"yr2QualificationDataTypeCode":"A","yr2PercentageValue":7.9,"yr3QualificationDataYear":2022,"yr3QualificationDataTypeCode":"A","yr3PercentageValue":1.5},{"qualificationYear":2020,"averagePercentValue":3.1,"yr1QualificationDataYear":2017,"yr1QualificationDataTypeCode":"A","yr1PercentageValue":2,"yr2QualificationDataYear":2018,"yr2QualificationDataTypeCode":"A","yr2PercentageValue":3.5,"yr3QualificationDataYear":2019,"yr3QualificationDataTypeCode":"A","yr3PercentageValue":3.8}]}]}]}