{
  "orisCode": 8906,
  "certificationEventData": [],
  "testExtensionExemptionData": [],
  "testSummaryData": [
    {

      "airEmissionTestData": [],
      "appendixECorrelationTestSummaryData": [],
      "beginDate": "2018-09-06",
      "beginHour": 9,
      "beginMinute": 34,
      "calibrationInjectionData": [],
      "componentId": "214",
      "cycleTimeSummaryData": [],
      "endDate": "2018-09-06",
      "endHour": 10,
      "endMinute": 18,
      "flowToLoadCheckData": [],
      "flowToLoadReferenceData": [],
      "fuelFlowmeterAccuracyData": [],
      "fuelFlowToLoadBaselineData": [],
      "fuelFlowToLoadTestData": [],
      "gracePeriodIndicator": 0,
      "hgSummaryData": [],
      "injectionProtocolCode": null,
      "linearitySummaryData": [],
      "quarter": null,
      "rataData": [
        {
          "numberOfLoadLevels": 1,
          "overallBiasAdjustmentFactor": 1.000,
          "rataFrequencyCode": "4QTRS",
          "rataSummaryData": [
            {
              "apsCode": null,
              "apsIndicator": 0,
              "averageGrossUnitLoad": 62.0,
              "biasAdjustmentFactor": 1.000,
              "calculatedWAF": null,
              "co2OrO2ReferenceMethodCode": null,
              "confidenceCoefficient": 0.00100,
              "defaultWAF": null,
              "meanCEMValue": 0.07300,
              "meanDifference": -0.00300,
              "meanRATAReferenceValue": 0.07000,
              "numberOfTraversePoints": null,
              "operatingLevelCode": "N",
              "rataRunData": [
                {
                  "beginDate": "2018-08-28",
                  "beginHour": 21,
                  "beginMinute": 40,
                  "cemValue": 0.07300,
                  "endDate": "2018-08-28",
                  "endHour": 22,
                  "endMinute": 0,
                  "flowRataRunData": [],
                  "grossUnitLoad": 62.0,
                  "rataReferenceValue": 0.06800,
                  "runNumber": 1,
                  "runStatusCode": "NOTUSED"
                },
                {
                  "beginDate": "2018-08-28",
                  "beginHour": 22,
                  "beginMinute": 13,
                  "cemValue": 0.07400,
                  "endDate": "2018-08-28",
                  "endHour": 22,
                  "endMinute": 33,
                  "flowRataRunData": [],
                  "grossUnitLoad": 61.0,
                  "rataReferenceValue": 0.07000,
                  "runNumber": 2,
                  "runStatusCode": "RUNUSED"
                },
                {
                  "beginDate": "2018-08-28",
                  "beginHour": 22,
                  "beginMinute": 46,
                  "cemValue": 0.07300,
                  "endDate": "2018-08-28",
                  "endHour": 23,
                  "endMinute": 6,
                  "flowRataRunData": [],
                  "grossUnitLoad": 62.0,
                  "rataReferenceValue": 0.06900,
                  "runNumber": 3,
                  "runStatusCode": "RUNUSED"
                },
                {
                  "beginDate": "2018-08-28",
                  "beginHour": 23,
                  "beginMinute": 27,
                  "cemValue": 0.07300,
                  "endDate": "2018-08-28",
                  "endHour": 23,
                  "endMinute": 47,
                  "flowRataRunData": [],
                  "grossUnitLoad": 62.0,
                  "rataReferenceValue": 0.07000,
                  "runNumber": 4,
                  "runStatusCode": "RUNUSED"
                },
                {
                  "beginDate": "2018-08-29",
                  "beginHour": 0,
                  "beginMinute": 1,
                  "cemValue": 0.07200,
                  "endDate": "2018-08-29",
                  "endHour": 0,
                  "endMinute": 21,
                  "flowRataRunData": [],
                  "grossUnitLoad": 62.0,
                  "rataReferenceValue": 0.06900,
                  "runNumber": 5,
                  "runStatusCode": "RUNUSED"
                },
                {
                  "beginDate": "2018-08-29",
                  "beginHour": 0,
                  "beginMinute": 33,
                  "cemValue": 0.07300,
                  "endDate": "2018-08-29",
                  "endHour": 0,
                  "endMinute": 53,
                  "flowRataRunData": [],
                  "grossUnitLoad": 62.0,
                  "rataReferenceValue": 0.06900,
                  "runNumber": 6,
                  "runStatusCode": "RUNUSED"
                },
                {
                  "beginDate": "2018-08-29",
                  "beginHour": 1,
                  "beginMinute": 5,
                  "cemValue": 0.07300,
                  "endDate": "2018-08-29",
                  "endHour": 1,
                  "endMinute": 25,
                  "flowRataRunData": [],
                  "grossUnitLoad": 62.0,
                  "rataReferenceValue": 0.06800,
                  "runNumber": 7,
                  "runStatusCode": "RUNUSED"
                },
                {
                  "beginDate": "2018-08-29",
                  "beginHour": 1,
                  "beginMinute": 36,
                  "cemValue": 0.07300,
                  "endDate": "2018-08-29",
                  "endHour": 1,
                  "endMinute": 56,
                  "flowRataRunData": [],
                  "grossUnitLoad": 62.0,
                  "rataReferenceValue": 0.07000,
                  "runNumber": 8,
                  "runStatusCode": "RUNUSED"
                },
                {
                  "beginDate": "2018-08-29",
                  "beginHour": 2,
                  "beginMinute": 9,
                  "cemValue": 0.07300,
                  "endDate": "2018-08-29",
                  "endHour": 2,
                  "endMinute": 29,
                  "flowRataRunData": [],
                  "grossUnitLoad": 62.0,
                  "rataReferenceValue": 0.07200,
                  "runNumber": 9,
                  "runStatusCode": "RUNUSED"
                },
                {
                  "beginDate": "2018-08-29",
                  "beginHour": 2,
                  "beginMinute": 37,
                  "cemValue": 0.07300,
                  "endDate": "2018-08-29",
                  "endHour": 2,
                  "endMinute": 57,
                  "flowRataRunData": [],
                  "grossUnitLoad": 62.0,
                  "rataReferenceValue": 0.07200,
                  "runNumber": 10,
                  "runStatusCode": "RUNUSED"
                }
              ],
              "referenceMethodCode": "7E,3A",
              "relativeAccuracy": 5.95,
              "stackArea": null,
              "stackDiameter": null,
              "standardDeviationDifference": 0.00100,
              "tValue": 2.306
            }
          ],
          "relativeAccuracy": 5.95
        }
      ],
      "spanScaleCode": null,
      "stackPipeId": null,
      "testComment": null,
      "testDescription": null,
      "testNumber": "211-Q3-2018-001",
      "testQualificationData": [],
      "testReasonCode": "QA",
      "testResultCode": "PASSED",
      "testTypeCode": "RATA",
      "transmitterTransducerData": [],
      "unitDefaultTestData": [],
      "unitId": "20",
      "year": null
    }
  ],
  "version": 0,
  "matsQuarterlyCompliance": {
    "unitInformation": [],
    "complianceAverages": [],
    "deviations": [],
    "performanceTestSummaryData": []
  }
}